setup.py
cqhttp/__init__.py
cqhttp.egg-info/PKG-INFO
cqhttp.egg-info/SOURCES.txt
cqhttp.egg-info/dependency_links.txt
cqhttp.egg-info/requires.txt
cqhttp.egg-info/top_level.txt