Metadata-Version: 1.0
Name: cqhttp
Version: 1.0.1
Summary: CQHttp Python SDK
Home-page: https://github.com/richardchien/cqhttp-python-sdk
Author: Richard Chien
Author-email: richardchienthebest@gmail.com
License: MIT License
Platform: any
